manowar_agent-2020.8.4.data/data/etc/manowar_agent/collector.yaml
manowar_agent-2020.8.4.data/data/etc/manowar_agent/minion
manowar_agent-2020.8.4.data/data/etc/manowar_agent/saltcell.yaml
manowar_agent-2020.8.4.data/data/etc/manowar_agent/state/_modules/platpi.py
manowar_agent-2020.8.4.data/scripts/manowar_agent
saltcell/__init__.py
saltcell/clientcollector.py
saltcell/mown.py
manowar_agent-2020.8.4.dist-info/LICENSE
manowar_agent-2020.8.4.dist-info/METADATA
manowar_agent-2020.8.4.dist-info/WHEEL
manowar_agent-2020.8.4.dist-info/top_level.txt
manowar_agent-2020.8.4.dist-info/RECORD
